convolutional_autoencoder_pytorch/__init__.py
convolutional_autoencoder_pytorch/module.py
convolutional_autoencoder_pytorch-1.0.1.dist-info/licenses/LICENSE
convolutional_autoencoder_pytorch-1.0.1.dist-info/METADATA
convolutional_autoencoder_pytorch-1.0.1.dist-info/WHEEL
convolutional_autoencoder_pytorch-1.0.1.dist-info/top_level.txt
convolutional_autoencoder_pytorch-1.0.1.dist-info/RECORD
